artext/__init__.py
artext/__main__.py
artext/artext.py
artext/config.py
artext/inflect.py
artext/utils.py
artext/word_level.py
artext-0.2.9.dist-info/LICENSE
artext-0.2.9.dist-info/METADATA
artext-0.2.9.dist-info/WHEEL
artext-0.2.9.dist-info/entry_points.txt
artext-0.2.9.dist-info/top_level.txt
artext-0.2.9.dist-info/RECORD
