Metadata-Version: 2.1
Name: artext
Version: 0.2.9
Summary: Probabilistic Noising of Natural Language
Home-page: https://github.com/fgaim/artext
Author: Fitsum Gaim
Author-email: fitsum@geezlab.com
License: UNKNOWN
Platform: UNKNOWN
Classifier: Programming Language :: Python :: 3
Classifier: License :: OSI Approved :: MIT License
Classifier: Operating System :: OS Independent
